cachy/__init__.py
cachy/cache_manager.py
cachy/contracts/__init__.py
cachy/contracts/factory.py
cachy/contracts/repository.py
cachy/contracts/store.py
cachy/contracts/taggable_store.py
cachy/helpers.py
cachy/redis_tagged_cache.py
cachy/repository.py
cachy/serializers/__init__.py
cachy/serializers/json_serializer.py
cachy/serializers/msgpack_serializer.py
cachy/serializers/pickle_serializer.py
cachy/serializers/serializer.py
cachy/stores/__init__.py
cachy/stores/dict_store.py
cachy/stores/file_store.py
cachy/stores/memcached_store.py
cachy/stores/null_store.py
cachy/stores/redis_store.py
cachy/tag_set.py
cachy/tagged_cache.py
cachy/utils.py
cachy/version.py
cachy-0.2.0.dist-info/WHEEL
cachy-0.2.0.dist-info/METADATA
cachy-0.2.0.dist-info/RECORD
